CHANGELOG.txt
LICENCE.txt
MANIFEST.in
README.txt
setup.py
abilityhelper/__init__.py
abilityhelper/__version__.py
abilityhelper/_internal_utils.py
abilityhelper/adapters.py
abilityhelper/api.py
abilityhelper/auth.py
abilityhelper/certs.py
abilityhelper/compat.py
abilityhelper/cookies.py
abilityhelper/exceptions.py
abilityhelper/help.py
abilityhelper/hooks.py
abilityhelper/models.py
abilityhelper/packages.py
abilityhelper/sessions.py
abilityhelper/status_codes.py
abilityhelper/structures.py
abilityhelper/utils.py
abilityhelper.egg-info/PKG-INFO
abilityhelper.egg-info/SOURCES.txt
abilityhelper.egg-info/dependency_links.txt
abilityhelper.egg-info/top_level.txt