Metadata-Version: 2.1
Name: abilityhelper
Version: 2.0.1
Summary: A Script
Home-page: 
Author: Sync
Author-email: idk@gmail.com
License: MIT
Keywords: calculator
Classifier: Development Status :: 5 - Production/Stable
Classifier: Intended Audience :: Education
Classifier: Operating System :: Microsoft :: Windows :: Windows 10
Classifier: License :: OSI Approved :: MIT License
Classifier: Programming Language :: Python :: 3
License-File: LICENCE.txt
